README.rst
container_whooshalchemyplus.py
setup.cfg
setup.py
Container_WhooshAlchemyPlus.egg-info/PKG-INFO
Container_WhooshAlchemyPlus.egg-info/SOURCES.txt
Container_WhooshAlchemyPlus.egg-info/dependency_links.txt
Container_WhooshAlchemyPlus.egg-info/not-zip-safe
Container_WhooshAlchemyPlus.egg-info/top_level.txt
test/test_all.py