Metadata-Version: 1.1
Name: Container-WhooshAlchemyPlus
Version: 0.7.5.post3
Summary: Whoosh extension to Flask/SQLAlchemy which used in sina container
Home-page: UNKNOWN
Author: UNKNOWN
Author-email: UNKNOWN
License: UNKNOWN
Platform: any
Classifier: Environment :: Web Environment
Classifier: Intended Audience :: Developers
Classifier: License :: OSI Approved :: BSD License
Classifier: Operating System :: OS Independent
Classifier: Programming Language :: Python
Classifier: Topic :: Internet :: WWW/HTTP :: Dynamic Content
Classifier: Topic :: Software Development :: Libraries :: Python Modules
Provides: container_whooshalchemyplus
